example_mas/__init__.py
example_mas/mosaik.py
example_sim/__init__.py
example_sim/mosaik.py
example_sim/simulator.py
mosaik_api/__init__.py
mosaik_api/datetime.py
mosaik_api-3.0.6.dist-info/AUTHORS.txt
mosaik_api-3.0.6.dist-info/LICENSE.txt
mosaik_api-3.0.6.dist-info/METADATA
mosaik_api-3.0.6.dist-info/WHEEL
mosaik_api-3.0.6.dist-info/entry_points.txt
mosaik_api-3.0.6.dist-info/top_level.txt
mosaik_api-3.0.6.dist-info/RECORD
